MANIFEST.in
README.md
dev.txt
setup.py
sku_vault_api/__init__.py
sku_vault_api/client.py
sku_vault_api/version_info.py
sku_vault_api.egg-info/PKG-INFO
sku_vault_api.egg-info/SOURCES.txt
sku_vault_api.egg-info/dependency_links.txt
sku_vault_api.egg-info/requires.txt
sku_vault_api.egg-info/top_level.txt